russian_numerals/__init__.py
russian_numerals/handlers.py
russian_numerals-0.2b0.data/scripts/russian-numerals
russian_numerals-0.2b0.dist-info/AUTHORS
russian_numerals-0.2b0.dist-info/LICENSE
russian_numerals-0.2b0.dist-info/METADATA
russian_numerals-0.2b0.dist-info/WHEEL
russian_numerals-0.2b0.dist-info/top_level.txt
russian_numerals-0.2b0.dist-info/RECORD
